opengris_scaler.libs/libcapnp-1-137b6426.0.1.so
opengris_scaler.libs/libkj-1-c3197b44.0.1.so
scaler/__init__.py
scaler/about.py
scaler/version.txt
scaler/client/__init__.py
scaler/client/client.py
scaler/client/future.py
scaler/client/object_buffer.py
scaler/client/object_reference.py
scaler/client/agent/__init__.py
scaler/client/agent/client_agent.py
scaler/client/agent/disconnect_manager.py
scaler/client/agent/future_manager.py
scaler/client/agent/heartbeat_manager.py
scaler/client/agent/mixins.py
scaler/client/agent/object_manager.py
scaler/client/agent/task_manager.py
scaler/client/serializer/__init__.py
scaler/client/serializer/default.py
scaler/client/serializer/mixins.py
scaler/cluster/__init__.py
scaler/cluster/cluster.py
scaler/cluster/combo.py
scaler/cluster/object_storage_server.py
scaler/cluster/scheduler.py
scaler/compat/__init__.py
scaler/compat/ray.py
scaler/config/__init__.py
scaler/config/config_class.py
scaler/config/defaults.py
scaler/config/mixins.py
scaler/config/common/__init__.py
scaler/config/common/logging.py
scaler/config/common/web.py
scaler/config/common/worker.py
scaler/config/common/worker_adapter.py
scaler/config/section/__init__.py
scaler/config/section/cluster.py
scaler/config/section/ecs_worker_adapter.py
scaler/config/section/native_worker_adapter.py
scaler/config/section/object_storage_server.py
scaler/config/section/scheduler.py
scaler/config/section/symphony_worker_adapter.py
scaler/config/section/top.py
scaler/config/section/webui.py
scaler/config/types/__init__.py
scaler/config/types/network_backend.py
scaler/config/types/object_storage_server.py
scaler/config/types/worker.py
scaler/config/types/zmq.py
scaler/entry_points/__init__.py
scaler/entry_points/cluster.py
scaler/entry_points/object_storage_server.py
scaler/entry_points/scheduler.py
scaler/entry_points/top.py
scaler/entry_points/webui.py
scaler/entry_points/worker_adapter_ecs.py
opengris_scaler-1.12.43.dist-info/METADATA
opengris_scaler-1.12.43.dist-info/WHEEL
opengris_scaler-1.12.43.dist-info/entry_points.txt
opengris_scaler-1.12.43.dist-info/RECORD
opengris_scaler-1.12.43.dist-info/licenses/LICENSE
opengris_scaler-1.12.43.dist-info/licenses/LICENSE.spdx
opengris_scaler-1.12.43.dist-info/licenses/NOTICE
